{
  "title": "Пророк",
  "type": "poem",
  "date": "2026-07-06",
  "section": "lyrics",
  "text": [
    [
      "Кирпич летит в окно — финал... А перед этим",
      "Я плакал, я кричал, просил и умолял...",
      "Не надо! Перестаньте! Оставьте выбор детям!",
      "Меня не замечали... Теперь — горит земля."
    ],
    [
      "Теперь огонь повсюду... Вода — смертельный яд...",
      "За ваш безумный выбор, за вашу блажь и дичь!",
      "Вы двигались беспечно, уверенно но, в ад!",
      "Теперь уж слишком поздно... Теперь — летит кирпич..."
    ]
  ]
}
